[
  {
    "_id": "6930124da494596ad6f5695c",
    "coverages": [
      "AE",
      "AL",
      "AT",
      "AU",
      "BE",
      "BG",
      "BR",
      "CA",
      "CH",
      "CN",
      "CY",
      "CZ",
      "DE",
      "DK",
      "EE",
      "ES",
      "FI",
      "FR",
      "GB",
      "GE",
      "GI",
      "GP",
      "GR",
      "HK",
      "HR",
      "HU",
      "ID",
      "IE",
      "IL",
      "IN",
      "IS",
      "IT",
      "JE",
      "JP",
      "KR",
      "KZ",
      "LI",
      "LT",
      "LU",
      "LV",
      "MO",
      "MT",
      "MX",
      "MY",
      "NL",
      "NO",
      "NZ",
      "PH",
      "PL",
      "PT",
      "RE",
      "RO",
      "RS",
      "RU",
      "SE",
      "SG",
      "SI",
      "SK",
      "TH",
      "TR",
      "TW",
      "US",
      "ZA"
    ],
    "numberCoveredCountry": 63,
    "enName": "FairPlay FirstFill FREE 1 GB 180 DAYS",
    "name": "FairPlay FirstFill FREE 1 GB 180 DAYS",
    "price_info": "",
    "capacity_info": "",
    "validity_info": "",
    "additionalInfo": "\u2022 No payment details needed\n\u2022 No more eSIM swaps!\n\u2022 5G high-speed internet\n\u2022 eSIM 2 x re-activatable after deletion\n\u2022 Auto renewal: OFF",
    "capacity": 1000,
    "period": 180,
    "prices": {
      "EUR": 0
    },
    "subscription": false,
    "subscription_period": null,
    "phone_number": false,
    "telephony": null,
    "canTopUp": true,
    "eKYC": false,
    "tethering": true,
    "internetBreakouts": [],
    "dataCapPer": null,
    "speedLimit": null,
    "reducedSpeed": null,
    "possibleThrottling": false,
    "promoEnabled": false,
    "provider": "69007ec7060073f43b25c6a8",
    "hasAds": false,
    "payAsYouGo": false,
    "newUserOnly": false,
    "isConsecutive": false,
    "networkTypes": [],
    "isLowLatency": false,
    "has5G": false,
    "usdPrice": 0,
    "promoPrices": {},
    "usdPromoPrice": null
  },
  {
    "_id": "68da51a49ecaacd99c74ac8d",
    "coverages": [
      "AL",
      "AT",
      "BA",
      "BE",
      "BG",
      "CH",
      "CY",
      "CZ",
      "DE",
      "DK",
      "EE",
      "ES",
      "FI",
      "FR",
      "GB",
      "GI",
      "GR",
      "HR",
      "HU",
      "IE",
      "IS",
      "IT",
      "KK",
      "LI",
      "LT",
      "LU",
      "LV",
      "ME",
      "MT",
      "NL",
      "NO",
      "PL",
      "PT",
      "RO",
      "SE",
      "SI",
      "SK",
      "SM",
      "TR"
    ],
    "numberCoveredCountry": 39,
    "enName": "FREE Europe eSIM &amp; Data",
    "name": "FREE Europe eSIM &amp; Data",
    "price_info": "Enjoy your free trial :)",
    "capacity_info": "No throttling.",
    "validity_info": "30-day free trial starts upon eSIM activation.",
    "additionalInfo": "Roamless eSIM can be used globally.\neSIM can be activated immediately. If needed, eSIM can be deleted and re-activated. You won't lose your Flex Credits or Fix Plans even if you delete your eSIM.",
    "capacity": 525,
    "period": 30,
    "prices": {
      "USD": 0
    },
    "subscription": false,
    "subscription_period": null,
    "phone_number": false,
    "telephony": null,
    "canTopUp": true,
    "eKYC": null,
    "tethering": true,
    "internetBreakouts": [
      {
        "country": "BE"
      },
      {
        "country": "FR"
      }
    ],
    "dataCapPer": null,
    "speedLimit": null,
    "reducedSpeed": null,
    "possibleThrottling": false,
    "promoEnabled": false,
    "provider": "66e18e73597f9c6d753b7571",
    "hasAds": false,
    "payAsYouGo": true,
    "newUserOnly": true,
    "isConsecutive": false,
    "networkTypes": [],
    "isLowLatency": false,
    "has5G": false,
    "usdPrice": 0,
    "promoPrices": {
      "USD": 0
    },
    "usdPromoPrice": 0
  },
  {
    "_id": "68db84cbc7d163c6f6a93e24",
    "coverages": [
      "AT",
      "BA",
      "BE",
      "BG",
      "CH",
      "CY",
      "CZ",
      "DE",
      "DK",
      "EE",
      "ES",
      "FI",
      "FO",
      "FR",
      "GB",
      "GI",
      "GR",
      "HR",
      "HU",
      "IE",
      "IS",
      "IT",
      "LI",
      "LT",
      "LU",
      "LV",
      "MD",
      "ME",
      "MK",
      "MT",
      "NL",
      "NO",
      "PL",
      "PT",
      "RO",
      "RS",
      "SE",
      "SI",
      "SK",
      "TR",
      "UA",
      "XK"
    ],
    "numberCoveredCountry": 42,
    "enName": "Europe",
    "name": "Europe",
    "price_info": "",
    "capacity_info": "",
    "validity_info": "",
    "additionalInfo": "",
    "capacity": 500,
    "period": 7,
    "prices": {
      "USD": 0
    },
    "subscription": false,
    "subscription_period": null,
    "phone_number": false,
    "telephony": null,
    "canTopUp": null,
    "eKYC": null,
    "tethering": null,
    "internetBreakouts": [
      {
        "country": "DK"
      },
      {
        "country": "US"
      }
    ],
    "dataCapPer": null,
    "speedLimit": null,
    "reducedSpeed": null,
    "possibleThrottling": false,
    "promoEnabled": false,
    "provider": "5c89d6b91144d06205595375",
    "hasAds": false,
    "payAsYouGo": false,
    "newUserOnly": false,
    "isConsecutive": false,
    "networkTypes": [],
    "isLowLatency": false,
    "has5G": false,
    "usdPrice": 0,
    "promoPrices": {
      "USD": 0
    },
    "usdPromoPrice": 0
  },
  {
    "_id": "6910b30ec1cfe99cf3045b14",
    "coverages": [
      "AD",
      "AG",
      "AI",
      "AL",
      "AM",
      "AR",
      "AT",
      "AU",
      "AZ",
      "BA",
      "BB",
      "BD",
      "BE",
      "BG",
      "BH",
      "BL",
      "BR",
      "BY",
      "CA",
      "CH",
      "CL",
      "CN",
      "CR",
      "CY",
      "CZ",
      "DE",
      "DK",
      "DM",
      "EC",
      "EE",
      "ES",
      "FI",
      "FO",
      "FR",
      "GB",
      "GD",
      "GE",
      "GF",
      "GG",
      "GI",
      "GP",
      "GR",
      "HK",
      "HR",
      "HU",
      "ID",
      "IE",
      "IL",
      "IS",
      "IT",
      "JP",
      "KG",
      "KH",
      "KN",
      "KR",
      "KW",
      "KY",
      "KZ",
      "LC",
      "LI",
      "LK",
      "LT",
      "LU",
      "LV",
      "MD",
      "ME",
      "MF",
      "MG",
      "MK",
      "MO",
      "MT",
      "MU",
      "MW",
      "MX",
      "MY",
      "NL",
      "NO",
      "NP",
      "NZ",
      "PA",
      "PE",
      "PH",
      "PT",
      "PY",
      "QA",
      "RE",
      "RO",
      "RS",
      "SE",
      "SG",
      "SI",
      "SK",
      "SV",
      "TD",
      "TH",
      "TR",
      "UA",
      "US",
      "UY",
      "UZ",
      "VC",
      "VN",
      "XK",
      "ZA"
    ],
    "numberCoveredCountry": 104,
    "enName": "iRoamly-eSIM-500MB-1 Day-Daily-Free",
    "name": "iRoamly-eSIM-500MB-1 Day-Daily-Free",
    "price_info": "",
    "capacity_info": "",
    "validity_info": "",
    "additionalInfo": "500MB high-speed per day, then reduced to 384kbps",
    "capacity": 500,
    "period": 1,
    "prices": {
      "USD": 0
    },
    "subscription": false,
    "subscription_period": null,
    "phone_number": false,
    "telephony": null,
    "canTopUp": false,
    "eKYC": false,
    "tethering": true,
    "internetBreakouts": [],
    "dataCapPer": null,
    "speedLimit": null,
    "reducedSpeed": null,
    "possibleThrottling": false,
    "promoEnabled": false,
    "provider": "66ac21966d047ed956f30520",
    "hasAds": false,
    "payAsYouGo": false,
    "newUserOnly": true,
    "isConsecutive": false,
    "networkTypes": [],
    "isLowLatency": false,
    "has5G": false,
    "usdPrice": 0,
    "promoPrices": {},
    "usdPromoPrice": null
  },
  {
    "_id": "68f7a57d1a37c4b60a8c4d34",
    "coverages": [
      "AT",
      "BE",
      "BG",
      "CH",
      "CY",
      "CZ",
      "DE",
      "DK",
      "EE",
      "ES",
      "FI",
      "FR",
      "GB",
      "GR",
      "HR",
      "HU",
      "IE",
      "IL",
      "IS",
      "IT",
      "LI",
      "LT",
      "LU",
      "LV",
      "MT",
      "NL",
      "NO",
      "PL",
      "PT",
      "RO",
      "SE",
      "SI",
      "SK",
      "TR",
      "UA"
    ],
    "numberCoveredCountry": 35,
    "enName": "Corvus Europe",
    "name": "Corvus Europe",
    "price_info": "",
    "capacity_info": "",
    "validity_info": "",
    "additionalInfo": "",
    "capacity": 100,
    "period": 7,
    "prices": {
      "USD": 0
    },
    "subscription": false,
    "subscription_period": null,
    "phone_number": false,
    "telephony": null,
    "canTopUp": true,
    "eKYC": false,
    "tethering": true,
    "internetBreakouts": [],
    "dataCapPer": null,
    "speedLimit": null,
    "reducedSpeed": null,
    "possibleThrottling": false,
    "promoEnabled": false,
    "provider": "61092d9ae3da2061875bc429",
    "hasAds": false,
    "payAsYouGo": false,
    "newUserOnly": true,
    "isConsecutive": false,
    "networkTypes": [],
    "isLowLatency": false,
    "has5G": false,
    "usdPrice": 0,
    "promoPrices": {},
    "usdPromoPrice": null
  }
]